{
    "brands": [{
            "brandName": "apple",
            "brandID": "iphone",
            "ID": "A01",
            "pic": "../images/iphone11.png",
            "pic1": "../images/iphone11.png",
            "pic2": "../images/iphone12.png",
            "pic3": "../images/iphone13.png",
            "pic4": "../images/iphone13pro.png",
            "name": "Apple Iphone 11",
            "price": 670,
            "discount": 570,
            "dispercent": 25,
            "gift": "Discount 15%",
            "body": "Aluminum frame, Gorilla Glass front with oleophobic coating, Gorilla Glass back with glossy finish, IP68 certified for water and dust resistance. Black, Green, Yellow, Purple, White, and Red color options.",
            "screen": "IPS LCD screen of 828 x 1792 px resolution, 326ppi, 625 nits, 120Hz touch sensing, wide color gamut. True Tone adjustment via a six-channel ambient light sensor.OS: Apple iOS 13 ",
            "os": "Apple iOS 13",
            "chipset": "Apple A13 Bionic chip (7nm+) - Hexa-core (2x2.66 GHz Lightning + 4x1.8 GHz Thunder) Apple CPU, four-core Apple GPU, 8-core Apple NPU 3-gen",
            "memory": "4GB of RAM; 64/128/256GB of internal storage",
            "camera": "Dual 12MP camera: 26mm main wide-angle, F/1.8, OIS, Dual Pixel AF; 13mm ultra wide-angle, F/2.4, 120-degree field of view; quad-LED flash with slow sync",
            "video": "2160p@60/30fps, 1080p@30/60/120/240fps video recording with wider dynamic range and spatial sound, OIS + EIS",
            "selfie": "Dual camera - 23mm 12MP F/2.2 front-facing camera with HDR mode + 3D TOF camera; 2160p@60/30fps, 1080p@30/60/120fps video recording with wider dynamic range and spatial sound, EIS, depth detection for Portrait mode",
            "connectivity": "Dual SIM, 4G LTE (1 Gbps); Wi-Fi a/b/g/n/ac/ax; Bluetooth 5.0; Lightning port; GPS with A-GPS, GLONASS, GALILEO, QZSS; NFC; Apple U1 chip ultrawideband",
            "battery": "3,110 mAh battery, 18W fast charging, Qi wireless charging",
            "misc": "Face ID through dedicated TrueDepth camera, stereo speakers, Taptic Engine"
        },
        {
            "brandName": "apple",
            "brandID": "iphone",
            "ID": "A02",
            "pic": "../images/iphone12.png",
            "pic1": "../images/iphone11.png",
            "pic2": "../images/iphone12.png",
            "pic3": "../images/iphone13.png",
            "pic4": "../images/iphone13pro.png",
            "name": "Apple Iphone 12",
            "price": 870,
            "discount": 770,
            "dispercent": 10,
            "gift": "Discount 20%",
            "body": "Aluminum frame with matte finish, Ceramic Shield front with oleophobic coating, Glass back with glossy finish, IP68 certified for water and dust resistance. Black, White, Green, Blue, Red color options. 146.7 x 71.5 x 7.4 mm, 164 g.",
            "screen": "6.1 Retina XDR OLED screen of 1170 x 2532 px resolution, 460ppi, 600 nits, 120Hz touch sensing. HDR10, Dolby Vision support, wide color gamut. True Tone.",
            "os": "Apple iOS 15",
            "chipset": "Apple A14 Bionic chip (5nm) - Hexa-core (2x3.1 GHz Firestorm + 4x1.8 GHz Icestorm with 3.1GHz Turboboost) Apple CPU, four-core Apple GPU, 16-core Apple NPU 4-gen",
            "memory": "4GB of RAM; 64/128/256GB of internal storage",
            "camera": "Dual 12MP camera: 26mm main wide-angle, F/1.6, OIS, Dual Pixel AF; 13mm ultrawide-angle, F/2.4, 120-degree field of view; dual-LED flash with slow sync. Night Mode, Smart HDR 3, Deep Fusion.",
            "video": "2160p@60/30fps, 1080p@30/60/120/240fps video recording with wider dynamic range and spatial sound, OIS + EIS, Dolby Vision (30fps only)",
            "selfie": "Dual camera - 23mm 12MP F/2.2 front-facing camera with HDR mode + 3D TOF camera; Night Mode, Smart HDR 3, Deep Fusion. 2160p@60/30fps, 1080p@30/60/120fps video recording with wider dynamic range and spatial sound, EIS.",
            "connectivity": "Dual SIM, 4G LTE (1 Gbps); Wi-Fi a/b/g/n/ac/ax; Bluetooth 5.0; Lightning port; GPS with A-GPS, GLONASS, GALILEO, QZSS; NFC; Apple U1 chip ultrawideband",
            "battery": "2,815 mAh battery, 20W fast charging, 15 Qi wireless charging (MagSafe)",
            "misc": "Face ID through dedicated TrueDepth camera, stereo speakers, Taptic Engine"
        },
        {
            "brandName": "apple",
            "brandID": "iphone",
            "ID": "A03",
            "pic": "../images/iphone13.png",
            "pic1": "../images/iphone11.png",
            "pic2": "../images/iphone12.png",
            "pic3": "../images/iphone13.png",
            "pic4": "../images/iphone13pro.png",
            "name": "Apple Iphone 13",
            "price": 970,
            "discount": 870,
            "dispercent": 15,
            "gift": "Discount 15%",
            "body": "146.7x71.5x7.7mm, 174g; Glass front (Gorilla Glass), glass back (Gorilla Glass), aluminum frame; IP68 dust/water resistant (up to 6m for 30 mins), Apple Pay (Visa, MasterCard, AMEX certified).",
            "screen": "6.10 Super Retina XDR OLED, HDR10, Dolby Vision, 800 nits (typ), 1200 nits (peak), 1170x2532px resolution, 19.48:9 aspect ratio, 460ppi; Wide color gamut, True-tone.",
            "os": "Apple iOS 15",
            "chipset": "Apple A15 Bionic (5 nm): Hexa-core (2x3.22 GHz Avalanche + 4xX.X GHz Blizzard); Apple GPU (4-core graphics).",
            "memory": "128GB 4GB RAM, 256GB 4GB RAM, 512GB 4GB RAM; NVMe.",
            "camera": "Wide (main): 12 MP, f/1.6, 26mm, 1.7µm, dual pixel PDAF, sensor-shift OIS; Ultra wide angle: 12 MP, f/2.4, 120˚, 13mm.",
            "video": "Rear camera: 4K@24/30/60fps, 1080p@30/60/120/240fps, HDR, Dolby Vision HDR (up to 60fps), stereo sound rec; Front camera: 4K@24/25/30/60fps, 1080p@30/60/120fps, gyro-EIS",
            "selfie": "Wide (main): 12 MP, f/2.2, 23mm, 1/3.6 ; Depth: SL 3D.",
            "connectivity": "Dual SIM, 4G LTE (1 Gbps); Wi-Fi a/b/g/n/ac/ax; Bluetooth 5.0; Lightning port; GPS with A-GPS, GLONASS, GALILEO, QZSS; NFC; Apple U1 chip ultrawideband",
            "battery": "3240mAh; Fast charging 20W, 50% in 30 min (advertised), USB Power Delivery 2.0, MagSafe wireless charging 15W, Qi magnetic fast wireless charging 7.5W.",
            "misc": " Face ID, accelerometer, gyro, proximity, compass, barometer; NFC; Siri natural language commands and dictation, Ultra Wideband (UWB) support."
        },
        {
            "brandName": "apple",
            "brandID": "iphone",
            "ID": "A04",
            "pic": "../images/iphone13pro.png",
            "pic1": "../images/iphone11.png",
            "pic2": "../images/iphone12.png",
            "pic3": "../images/iphone13.png",
            "pic4": "../images/iphone13pro.png",
            "name": "Apple Iphone 13 ProMax",
            "price": 970,
            "discount": 870,
            "dispercent": 15,
            "gift": "Discount 15%",
            "body": "160.8x78.1x7.7mm, 240g; Glass front (Gorilla Glass), glass back (Gorilla Glass), stainless steel frame; IP68 dust/water resistant (up to 6m for 30 mins), Apple Pay (Visa, MasterCard, AMEX certified).",
            "screen": "6.70 Super Retina XDR OLED, 120Hz, HDR10, Dolby Vision, 1000 nits (typ), 1200 nits (peak), 1284x2778px resolution, 19.47:9 aspect ratio, 458ppi; Wide color gamut, True-tone.",
            "os": "Apple iOS 15",
            "chipset": "Apple A15 Bionic (5 nm): Hexa-core (2x3.22 GHz Avalanche + 4xX.X GHz Blizzard); Apple GPU (4-core graphics).",
            "memory": "128GB 4GB RAM, 256GB 4GB RAM, 512GB 4GB RAM; NVMe.",
            "camera": "Wide (main): 12 MP, f/1.6, 26mm, 1.7µm, dual pixel PDAF, sensor-shift OIS; Ultra wide angle: 12 MP, f/2.4, 120˚, 13mm.",
            "video": "Rear camera: 4K@24/30/60fps, 1080p@30/60/120/240fps, HDR, Dolby Vision HDR (up to 60fps), stereo sound rec; Front camera: 4K@24/25/30/60fps, 1080p@30/60/120fps, gyro-EIS",
            "selfie": "Wide (main): 12 MP, f/2.2, 23mm, 1/3.6 ; Depth: SL 3D.",
            "connectivity": "Dual SIM, 4G LTE (1 Gbps); Wi-Fi a/b/g/n/ac/ax; Bluetooth 5.0; Lightning port; GPS with A-GPS, GLONASS, GALILEO, QZSS; NFC; Apple U1 chip ultrawideband",
            "battery": "4352mAh; Fast charging 27W, 50% in 30 min (advertised), USB Power Delivery 2.0, MagSafe wireless charging 15W, Qi magnetic fast wireless charging 7.5W.",
            "misc": " Face ID, accelerometer, gyro, proximity, compass, barometer; NFC; Siri natural language commands and dictation, Ultra Wideband (UWB) support."
        },
        {
            "brandName": "samsung",
            "brandID": "samsung",
            "ID": "S01",
            "pic": "../images/samsunggalaxys20.png",
            "pic1": "../images/samsunggalaxys20.png",
            "pic2": "../images/samsunggalaxys21plus.png",
            "pic3": "../images/samsunggalaxys23.png",
            "pic4": "../images/samsunggalaxys21.png",
            "name": "Samsung Galaxy S20",
            "price": 670,
            "discount": 570,
            "dispercent": 25,
            "gift": "Discount 15%",
            "body": "159.8x74.5x8.4mm, 190g; Glass front, plastic back, aluminum frame; Samsung Pay (Visa, MasterCard certified), IP68 dust/water resistant (up to 1.5m for 30 mins); Colors: Cloud Lavender, Cloud Mint, Cloud Navy, Cloud White, Cloud Red, Cloud Orange.",
            "screen": "6.5 Super AMOLED, 1080x2400px resolution, 20:9 aspect ratio, 407ppi; 120Hz refresh rate.",
            "os": "Android 10, One UI 2.5",
            "chipset": "Qualcomm SM8250 Snapdragon 865 (7 nm+): Octa-core (1x2.84 GHz Kryo 585 & 3x2.42 GHz Kryo 585 & 4x1.8 GHz Kryo 585); Adreno 650.",
            "memory": "128GB 6GB RAM, 128GB 8GB RAM, 256GB 8GB RAM; microSDXC (uses shared SIM slot).",
            "camera": "Wide (main): 12 MP, f/1.8, 26mm, 1/1.76, 1.8µm, Dual Pixel PDAF, OIS; Telephoto: 8 MP, f/2.4, 73mm, 1/4.5, 1.0µm, PDAF, OIS, 3x optical zoom; Ultra wide angle: 12 MP, f/2.2, 123˚, 13mm, 1/3.0, 1.12µm; LED flash, auto-HDR, panorama.",
            "video": "Rear camera: 4K, 1080p, gyro-EIS; Front camera: 4K, 1080p",
            "selfie": "32 MP, f/2.2, 26mm (wide), 1/2.74, 0.8µm; HDR",
            "connectivity": "Dual SIM, 4G LTE (1 Gbps); Wi-Fi a/b/g/n/ac/ax; Bluetooth 5.0; Lightning port; GPS with A-GPS, GLONASS, GALILEO, QZSS; NFC; Apple U1 chip ultrawideband",
            "battery": "4500mAh; Fast charging 25W, Fast wireless charging 15W, Reverse wireless charging 4.5W, USB Power Delivery 3.0.",
            "misc": "Fingerprint reader (under display, optical), accelerometer, gyro, proximity, compass, barometer; NFC; stereo speakers."
        },
        {
            "brandName": "samsung",
            "brandID": "samsung",
            "ID": "S02",
            "pic": "../images/samsunggalaxys21.png",
            "pic1": "../images/samsunggalaxys20.png",
            "pic2": "../images/samsunggalaxys21plus.png",
            "pic3": "../images/samsunggalaxys23.png",
            "pic4": "../images/samsunggalaxys21.png",
            "name": "Samsung Galaxy S21",
            "price": 870,
            "discount": 770,
            "dispercent": 25,
            "gift": "Discount 20%",
            "body": "159.8x74.5x8.4mm, 190g; Glass front, plastic back, aluminum frame; Samsung Pay (Visa, MasterCard certified), IP68 dust/water resistant (up to 1.5m for 30 mins); Colors: Cloud Lavender, Cloud Mint, Cloud Navy, Cloud White, Cloud Red, Cloud Orange.",
            "screen": "6.5 Super AMOLED, 1080x2400px resolution, 20:9 aspect ratio, 407ppi; 120Hz refresh rate.",
            "os": "Android 10, One UI 2.5",
            "chipset": "Qualcomm SM8250 Snapdragon 865 (7 nm+): Octa-core (1x2.84 GHz Kryo 585 & 3x2.42 GHz Kryo 585 & 4x1.8 GHz Kryo 585); Adreno 650.",
            "memory": "128GB 6GB RAM, 128GB 8GB RAM, 256GB 8GB RAM; microSDXC (uses shared SIM slot).",
            "camera": "Wide (main): 12 MP, f/1.8, 26mm, 1/1.76, 1.8µm, Dual Pixel PDAF, OIS; Telephoto: 8 MP, f/2.4, 73mm, 1/4.5, 1.0µm, PDAF, OIS, 3x optical zoom; Ultra wide angle: 12 MP, f/2.2, 123˚, 13mm, 1/3.0, 1.12µm; LED flash, auto-HDR, panorama.",
            "video": "Rear camera: 4K, 1080p, gyro-EIS; Front camera: 4K, 1080p",
            "selfie": "32 MP, f/2.2, 26mm (wide), 1/2.74, 0.8µm; HDR",
            "connectivity": "Dual SIM, 4G LTE (1 Gbps); Wi-Fi a/b/g/n/ac/ax; Bluetooth 5.0; Lightning port; GPS with A-GPS, GLONASS, GALILEO, QZSS; NFC; Apple U1 chip ultrawideband",
            "battery": "4500mAh; Fast charging 25W, Fast wireless charging 15W, Reverse wireless charging 4.5W, USB Power Delivery 3.0.",
            "misc": "Fingerprint reader (under display, optical), accelerometer, gyro, proximity, compass, barometer; NFC; stereo speakers."
        },
        {
            "brandName": "samsung",
            "brandID": "samsung",
            "ID": "S03",
            "pic": "../images/samsunggalaxys21plus.png",
            "pic1": "../images/samsunggalaxys20.png",
            "pic2": "../images/samsunggalaxys21plus.png",
            "pic3": "../images/samsunggalaxys23.png",
            "pic4": "../images/samsunggalaxys21.png",
            "name": "Samsung Galaxy S21 Plus",
            "price": 970,
            "discount": 870,
            "dispercent": 25,
            "gift": "Discount 25%",
            "body": "159.8x74.5x8.4mm, 190g; Glass front, plastic back, aluminum frame; Samsung Pay (Visa, MasterCard certified), IP68 dust/water resistant (up to 1.5m for 30 mins); Colors: Cloud Lavender, Cloud Mint, Cloud Navy, Cloud White, Cloud Red, Cloud Orange.",
            "screen": "6.5 Super AMOLED, 1080x2400px resolution, 20:9 aspect ratio, 407ppi; 120Hz refresh rate.",
            "os": "Android 10, One UI 2.5",
            "chipset": "Qualcomm SM8250 Snapdragon 865 (7 nm+): Octa-core (1x2.84 GHz Kryo 585 & 3x2.42 GHz Kryo 585 & 4x1.8 GHz Kryo 585); Adreno 650.",
            "memory": "128GB 6GB RAM, 128GB 8GB RAM, 256GB 8GB RAM; microSDXC (uses shared SIM slot).",
            "camera": "Wide (main): 12 MP, f/1.8, 26mm, 1/1.76, 1.8µm, Dual Pixel PDAF, OIS; Telephoto: 8 MP, f/2.4, 73mm, 1/4.5, 1.0µm, PDAF, OIS, 3x optical zoom; Ultra wide angle: 12 MP, f/2.2, 123˚, 13mm, 1/3.0, 1.12µm; LED flash, auto-HDR, panorama.",
            "video": "Rear camera: 4K, 1080p, gyro-EIS; Front camera: 4K, 1080p",
            "selfie": "32 MP, f/2.2, 26mm (wide), 1/2.74, 0.8µm; HDR",
            "connectivity": "Dual SIM, 4G LTE (1 Gbps); Wi-Fi a/b/g/n/ac/ax; Bluetooth 5.0; Lightning port; GPS with A-GPS, GLONASS, GALILEO, QZSS; NFC; Apple U1 chip ultrawideband",
            "battery": "4500mAh; Fast charging 25W, Fast wireless charging 15W, Reverse wireless charging 4.5W, USB Power Delivery 3.0.",
            "misc": "Fingerprint reader (under display, optical), accelerometer, gyro, proximity, compass, barometer; NFC; stereo speakers."
        },
        {
            "brandName": "samsung",
            "brandID": "samsung",
            "ID": "S04",
            "pic": "../images/samsunggalaxys23.png",
            "pic1": "../images/samsunggalaxys20.png",
            "pic2": "../images/samsunggalaxys21plus.png",
            "pic3": "../images/samsunggalaxys23.png",
            "pic4": "../images/samsunggalaxys21.png",
            "name": "Samsung Galaxy S23",
            "price": 970,
            "discount": 870,
            "dispercent": 25,
            "gift": "New",
            "body": "159.8x74.5x8.4mm, 190g; Glass front, plastic back, aluminum frame; Samsung Pay (Visa, MasterCard certified), IP68 dust/water resistant (up to 1.5m for 30 mins); Colors: Cloud Lavender, Cloud Mint, Cloud Navy, Cloud White, Cloud Red, Cloud Orange.",
            "screen": "6.5 Super AMOLED, 1080x2400px resolution, 20:9 aspect ratio, 407ppi; 120Hz refresh rate.",
            "os": "Android 10, One UI 2.5",
            "chipset": "Qualcomm SM8250 Snapdragon 865 (7 nm+): Octa-core (1x2.84 GHz Kryo 585 & 3x2.42 GHz Kryo 585 & 4x1.8 GHz Kryo 585); Adreno 650.",
            "memory": "128GB 6GB RAM, 128GB 8GB RAM, 256GB 8GB RAM; microSDXC (uses shared SIM slot).",
            "camera": "Wide (main): 12 MP, f/1.8, 26mm, 1/1.76, 1.8µm, Dual Pixel PDAF, OIS; Telephoto: 8 MP, f/2.4, 73mm, 1/4.5, 1.0µm, PDAF, OIS, 3x optical zoom; Ultra wide angle: 12 MP, f/2.2, 123˚, 13mm, 1/3.0, 1.12µm; LED flash, auto-HDR, panorama.",
            "video": "Rear camera: 4K, 1080p, gyro-EIS; Front camera: 4K, 1080p",
            "selfie": "32 MP, f/2.2, 26mm (wide), 1/2.74, 0.8µm; HDR",
            "connectivity": "Dual SIM, 4G LTE (1 Gbps); Wi-Fi a/b/g/n/ac/ax; Bluetooth 5.0; Lightning port; GPS with A-GPS, GLONASS, GALILEO, QZSS; NFC; Apple U1 chip ultrawideband",
            "battery": "4500mAh; Fast charging 25W, Fast wireless charging 15W, Reverse wireless charging 4.5W, USB Power Delivery 3.0.",
            "misc": "Fingerprint reader (under display, optical), accelerometer, gyro, proximity, compass, barometer; NFC; stereo speakers."
        },
        {
            "brandName": "google",
            "brandID": "google",
            "ID": "G01",
            "pic": "../images/pixel4a.png",
            "pic1": "../images/pixel4a.png",
            "pic2": "../images/pixel4xl.png",
            "pic3": "../images/pixel6.png",
            "pic4": "../images/pixel55G.png",
            "name": "Google Pixel 4A",
            "price": 670,
            "discount": 570,
            "dispercent": 25,
            "gift": "Discount 15%",
            "body": "159.8x74.5x8.4mm, 190g; Glass front, plastic back, aluminum frame; Samsung Pay (Visa, MasterCard certified), IP68 dust/water resistant (up to 1.5m for 30 mins); Colors: Cloud Lavender, Cloud Mint, Cloud Navy, Cloud White, Cloud Red, Cloud Orange.",
            "screen": "6.5 Super AMOLED, 1080x2400px resolution, 20:9 aspect ratio, 407ppi; 120Hz refresh rate.",
            "os": "Android 10, One UI 2.5",
            "chipset": "Qualcomm SM8250 Snapdragon 865 (7 nm+): Octa-core (1x2.84 GHz Kryo 585 & 3x2.42 GHz Kryo 585 & 4x1.8 GHz Kryo 585); Adreno 650.",
            "memory": "128GB 6GB RAM, 128GB 8GB RAM, 256GB 8GB RAM; microSDXC (uses shared SIM slot).",
            "camera": "Wide (main): 12 MP, f/1.8, 26mm, 1/1.76, 1.8µm, Dual Pixel PDAF, OIS; Telephoto: 8 MP, f/2.4, 73mm, 1/4.5, 1.0µm, PDAF, OIS, 3x optical zoom; Ultra wide angle: 12 MP, f/2.2, 123˚, 13mm, 1/3.0, 1.12µm; LED flash, auto-HDR, panorama.",
            "video": "Rear camera: 4K, 1080p, gyro-EIS; Front camera: 4K, 1080p",
            "selfie": "32 MP, f/2.2, 26mm (wide), 1/2.74, 0.8µm; HDR",
            "connectivity": "Dual SIM, 4G LTE (1 Gbps); Wi-Fi a/b/g/n/ac/ax; Bluetooth 5.0; Lightning port; GPS with A-GPS, GLONASS, GALILEO, QZSS; NFC; Apple U1 chip ultrawideband",
            "battery": "4500mAh; Fast charging 25W, Fast wireless charging 15W, Reverse wireless charging 4.5W, USB Power Delivery 3.0.",
            "misc": "Fingerprint reader (under display, optical), accelerometer, gyro, proximity, compass, barometer; NFC; stereo speakers."
        },
        {
            "brandName": "google",
            "brandID": "google",
            "ID": "G02",
            "pic": "../images/pixel4xl.png",
            "pic1": "../images/pixel4a.png",
            "pic2": "../images/pixel4xl.png",
            "pic3": "../images/pixel6.png",
            "pic4": "../images/pixel55G.png",
            "name": "Google Pixel 4XL",
            "price": 870,
            "discount": 770,
            "dispercent": 25,
            "gift": "Discount 20%",
            "body": "159.8x74.5x8.4mm, 190g; Glass front, plastic back, aluminum frame; Samsung Pay (Visa, MasterCard certified), IP68 dust/water resistant (up to 1.5m for 30 mins); Colors: Cloud Lavender, Cloud Mint, Cloud Navy, Cloud White, Cloud Red, Cloud Orange.",
            "screen": "6.5 Super AMOLED, 1080x2400px resolution, 20:9 aspect ratio, 407ppi; 120Hz refresh rate.",
            "os": "Android 10, One UI 2.5",
            "chipset": "Qualcomm SM8250 Snapdragon 865 (7 nm+): Octa-core (1x2.84 GHz Kryo 585 & 3x2.42 GHz Kryo 585 & 4x1.8 GHz Kryo 585); Adreno 650.",
            "memory": "128GB 6GB RAM, 128GB 8GB RAM, 256GB 8GB RAM; microSDXC (uses shared SIM slot).",
            "camera": "Wide (main): 12 MP, f/1.8, 26mm, 1/1.76, 1.8µm, Dual Pixel PDAF, OIS; Telephoto: 8 MP, f/2.4, 73mm, 1/4.5, 1.0µm, PDAF, OIS, 3x optical zoom; Ultra wide angle: 12 MP, f/2.2, 123˚, 13mm, 1/3.0, 1.12µm; LED flash, auto-HDR, panorama.",
            "video": "Rear camera: 4K, 1080p, gyro-EIS; Front camera: 4K, 1080p",
            "selfie": "32 MP, f/2.2, 26mm (wide), 1/2.74, 0.8µm; HDR",
            "connectivity": "Dual SIM, 4G LTE (1 Gbps); Wi-Fi a/b/g/n/ac/ax; Bluetooth 5.0; Lightning port; GPS with A-GPS, GLONASS, GALILEO, QZSS; NFC; Apple U1 chip ultrawideband",
            "battery": "4500mAh; Fast charging 25W, Fast wireless charging 15W, Reverse wireless charging 4.5W, USB Power Delivery 3.0.",
            "misc": "Fingerprint reader (under display, optical), accelerometer, gyro, proximity, compass, barometer; NFC; stereo speakers."
        },
        {
            "brandName": "google",
            "brandID": "google",
            "ID": "G03",
            "pic": "../images/pixel55G.png",
            "pic1": "../images/pixel4a.png",
            "pic2": "../images/pixel4xl.png",
            "pic3": "../images/pixel6.png",
            "pic4": "../images/pixel55G.png",
            "name": "Goolge pixel 5G",
            "price": 970,
            "discount": 870,
            "dispercent": 25,
            "gift": "Discount 25%",
            "body": "159.8x74.5x8.4mm, 190g; Glass front, plastic back, aluminum frame; Samsung Pay (Visa, MasterCard certified), IP68 dust/water resistant (up to 1.5m for 30 mins); Colors: Cloud Lavender, Cloud Mint, Cloud Navy, Cloud White, Cloud Red, Cloud Orange.",
            "screen": "6.5 Super AMOLED, 1080x2400px resolution, 20:9 aspect ratio, 407ppi; 120Hz refresh rate.",
            "os": "Android 10, One UI 2.5",
            "chipset": "Qualcomm SM8250 Snapdragon 865 (7 nm+): Octa-core (1x2.84 GHz Kryo 585 & 3x2.42 GHz Kryo 585 & 4x1.8 GHz Kryo 585); Adreno 650.",
            "memory": "128GB 6GB RAM, 128GB 8GB RAM, 256GB 8GB RAM; microSDXC (uses shared SIM slot).",
            "camera": "Wide (main): 12 MP, f/1.8, 26mm, 1/1.76, 1.8µm, Dual Pixel PDAF, OIS; Telephoto: 8 MP, f/2.4, 73mm, 1/4.5, 1.0µm, PDAF, OIS, 3x optical zoom; Ultra wide angle: 12 MP, f/2.2, 123˚, 13mm, 1/3.0, 1.12µm; LED flash, auto-HDR, panorama.",
            "video": "Rear camera: 4K, 1080p, gyro-EIS; Front camera: 4K, 1080p",
            "selfie": "32 MP, f/2.2, 26mm (wide), 1/2.74, 0.8µm; HDR",
            "connectivity": "Dual SIM, 4G LTE (1 Gbps); Wi-Fi a/b/g/n/ac/ax; Bluetooth 5.0; Lightning port; GPS with A-GPS, GLONASS, GALILEO, QZSS; NFC; Apple U1 chip ultrawideband",
            "battery": "4500mAh; Fast charging 25W, Fast wireless charging 15W, Reverse wireless charging 4.5W, USB Power Delivery 3.0.",
            "misc": "Fingerprint reader (under display, optical), accelerometer, gyro, proximity, compass, barometer; NFC; stereo speakers."
        },
        {
            "brandName": "google",
            "brandID": "google",
            "ID": "G04",
            "pic": "../images/pixel6.png",
            "pic1": "../images/pixel4a.png",
            "pic2": "../images/pixel4xl.png",
            "pic3": "../images/pixel6.png",
            "pic4": "../images/pixel55G.png",
            "name": "Goolge pixel 6",
            "price": 970,
            "discount": 870,
            "dispercent": 25,
            "gift": "Discount 25%",
            "body": "159.8x74.5x8.4mm, 190g; Glass front, plastic back, aluminum frame; Samsung Pay (Visa, MasterCard certified), IP68 dust/water resistant (up to 1.5m for 30 mins); Colors: Cloud Lavender, Cloud Mint, Cloud Navy, Cloud White, Cloud Red, Cloud Orange.",
            "screen": "6.5 Super AMOLED, 1080x2400px resolution, 20:9 aspect ratio, 407ppi; 120Hz refresh rate.",
            "os": "Android 10, One UI 2.5",
            "chipset": "Qualcomm SM8250 Snapdragon 865 (7 nm+): Octa-core (1x2.84 GHz Kryo 585 & 3x2.42 GHz Kryo 585 & 4x1.8 GHz Kryo 585); Adreno 650.",
            "memory": "128GB 6GB RAM, 128GB 8GB RAM, 256GB 8GB RAM; microSDXC (uses shared SIM slot).",
            "camera": "Wide (main): 12 MP, f/1.8, 26mm, 1/1.76, 1.8µm, Dual Pixel PDAF, OIS; Telephoto: 8 MP, f/2.4, 73mm, 1/4.5, 1.0µm, PDAF, OIS, 3x optical zoom; Ultra wide angle: 12 MP, f/2.2, 123˚, 13mm, 1/3.0, 1.12µm; LED flash, auto-HDR, panorama.",
            "video": "Rear camera: 4K, 1080p, gyro-EIS; Front camera: 4K, 1080p",
            "selfie": "32 MP, f/2.2, 26mm (wide), 1/2.74, 0.8µm; HDR",
            "connectivity": "Dual SIM, 4G LTE (1 Gbps); Wi-Fi a/b/g/n/ac/ax; Bluetooth 5.0; Lightning port; GPS with A-GPS, GLONASS, GALILEO, QZSS; NFC; Apple U1 chip ultrawideband",
            "battery": "4500mAh; Fast charging 25W, Fast wireless charging 15W, Reverse wireless charging 4.5W, USB Power Delivery 3.0.",
            "misc": "Fingerprint reader (under display, optical), accelerometer, gyro, proximity, compass, barometer; NFC; stereo speakers."
        },
        {
            "brandName": "motorola",
            "brandID": "motorola",
            "ID": "M01",
            "pic": "../images/motog.png",
            "pic1": "../images/motog.png",
            "pic2": "../images/motogpower.png",
            "pic3": "../images/motogstylelus.png",
            "pic4": "../images/motoone5gone.png",
            "name": "Motorola G",
            "price": 670,
            "discount": 570,
            "dispercent": 25,
            "gift": "Discount 15%",
            "body": "159.8x74.5x8.4mm, 190g; Glass front, plastic back, aluminum frame; Samsung Pay (Visa, MasterCard certified), IP68 dust/water resistant (up to 1.5m for 30 mins); Colors: Cloud Lavender, Cloud Mint, Cloud Navy, Cloud White, Cloud Red, Cloud Orange.",
            "screen": "6.5 Super AMOLED, 1080x2400px resolution, 20:9 aspect ratio, 407ppi; 120Hz refresh rate.",
            "os": "Android 10, One UI 2.5",
            "chipset": "Qualcomm SM8250 Snapdragon 865 (7 nm+): Octa-core (1x2.84 GHz Kryo 585 & 3x2.42 GHz Kryo 585 & 4x1.8 GHz Kryo 585); Adreno 650.",
            "memory": "128GB 6GB RAM, 128GB 8GB RAM, 256GB 8GB RAM; microSDXC (uses shared SIM slot).",
            "camera": "Wide (main): 12 MP, f/1.8, 26mm, 1/1.76, 1.8µm, Dual Pixel PDAF, OIS; Telephoto: 8 MP, f/2.4, 73mm, 1/4.5, 1.0µm, PDAF, OIS, 3x optical zoom; Ultra wide angle: 12 MP, f/2.2, 123˚, 13mm, 1/3.0, 1.12µm; LED flash, auto-HDR, panorama.",
            "video": "Rear camera: 4K, 1080p, gyro-EIS; Front camera: 4K, 1080p",
            "selfie": "32 MP, f/2.2, 26mm (wide), 1/2.74, 0.8µm; HDR",
            "connectivity": "Dual SIM, 4G LTE (1 Gbps); Wi-Fi a/b/g/n/ac/ax; Bluetooth 5.0; Lightning port; GPS with A-GPS, GLONASS, GALILEO, QZSS; NFC; Apple U1 chip ultrawideband",
            "battery": "4500mAh; Fast charging 25W, Fast wireless charging 15W, Reverse wireless charging 4.5W, USB Power Delivery 3.0.",
            "misc": "Fingerprint reader (under display, optical), accelerometer, gyro, proximity, compass, barometer; NFC; stereo speakers."
        },
        {
            "brandName": "motorola",
            "brandID": "motorola",
            "ID": "M02",
            "pic": "../images/motogpower.png",
            "pic1": "../images/motog.png",
            "pic2": "../images/motogpower.png",
            "pic3": "../images/motogstylelus.png",
            "pic4": "../images/motoone5gone.png",
            "name": "Motorola G Power",
            "price": 870,
            "discount": 770,
            "dispercent": 10,
            "gift": "Discount 20%",
            "body": "159.8x74.5x8.4mm, 190g; Glass front, plastic back, aluminum frame; Samsung Pay (Visa, MasterCard certified), IP68 dust/water resistant (up to 1.5m for 30 mins); Colors: Cloud Lavender, Cloud Mint, Cloud Navy, Cloud White, Cloud Red, Cloud Orange.",
            "screen": "6.5 Super AMOLED, 1080x2400px resolution, 20:9 aspect ratio, 407ppi; 120Hz refresh rate.",
            "os": "Android 10, One UI 2.5",
            "chipset": "Qualcomm SM8250 Snapdragon 865 (7 nm+): Octa-core (1x2.84 GHz Kryo 585 & 3x2.42 GHz Kryo 585 & 4x1.8 GHz Kryo 585); Adreno 650.",
            "memory": "128GB 6GB RAM, 128GB 8GB RAM, 256GB 8GB RAM; microSDXC (uses shared SIM slot).",
            "camera": "Wide (main): 12 MP, f/1.8, 26mm, 1/1.76, 1.8µm, Dual Pixel PDAF, OIS; Telephoto: 8 MP, f/2.4, 73mm, 1/4.5, 1.0µm, PDAF, OIS, 3x optical zoom; Ultra wide angle: 12 MP, f/2.2, 123˚, 13mm, 1/3.0, 1.12µm; LED flash, auto-HDR, panorama.",
            "video": "Rear camera: 4K, 1080p, gyro-EIS; Front camera: 4K, 1080p",
            "selfie": "32 MP, f/2.2, 26mm (wide), 1/2.74, 0.8µm; HDR",
            "connectivity": "Dual SIM, 4G LTE (1 Gbps); Wi-Fi a/b/g/n/ac/ax; Bluetooth 5.0; Lightning port; GPS with A-GPS, GLONASS, GALILEO, QZSS; NFC; Apple U1 chip ultrawideband",
            "battery": "4500mAh; Fast charging 25W, Fast wireless charging 15W, Reverse wireless charging 4.5W, USB Power Delivery 3.0.",
            "misc": "Fingerprint reader (under display, optical), accelerometer, gyro, proximity, compass, barometer; NFC; stereo speakers."
        },
        {
            "brandName": "motorola",
            "brandID": "motorola",
            "ID": "M03",
            "pic": "../images/motogstylelus.png",
            "pic1": "../images/motog.png",
            "pic2": "../images/motogpower.png",
            "pic3": "../images/motogstylelus.png",
            "pic4": "../images/motoone5gone.png",
            "name": "Motorola G Stylus",
            "price": 970,
            "discount": 870,
            "dispercent": 15,
            "gift": "Discount 15%",
            "body": "159.8x74.5x8.4mm, 190g; Glass front, plastic back, aluminum frame; Samsung Pay (Visa, MasterCard certified), IP68 dust/water resistant (up to 1.5m for 30 mins); Colors: Cloud Lavender, Cloud Mint, Cloud Navy, Cloud White, Cloud Red, Cloud Orange.",
            "screen": "6.5 Super AMOLED, 1080x2400px resolution, 20:9 aspect ratio, 407ppi; 120Hz refresh rate.",
            "os": "Android 10, One UI 2.5",
            "chipset": "Qualcomm SM8250 Snapdragon 865 (7 nm+): Octa-core (1x2.84 GHz Kryo 585 & 3x2.42 GHz Kryo 585 & 4x1.8 GHz Kryo 585); Adreno 650.",
            "memory": "128GB 6GB RAM, 128GB 8GB RAM, 256GB 8GB RAM; microSDXC (uses shared SIM slot).",
            "camera": "Wide (main): 12 MP, f/1.8, 26mm, 1/1.76, 1.8µm, Dual Pixel PDAF, OIS; Telephoto: 8 MP, f/2.4, 73mm, 1/4.5, 1.0µm, PDAF, OIS, 3x optical zoom; Ultra wide angle: 12 MP, f/2.2, 123˚, 13mm, 1/3.0, 1.12µm; LED flash, auto-HDR, panorama.",
            "video": "Rear camera: 4K, 1080p, gyro-EIS; Front camera: 4K, 1080p",
            "selfie": "32 MP, f/2.2, 26mm (wide), 1/2.74, 0.8µm; HDR",
            "connectivity": "Dual SIM, 4G LTE (1 Gbps); Wi-Fi a/b/g/n/ac/ax; Bluetooth 5.0; Lightning port; GPS with A-GPS, GLONASS, GALILEO, QZSS; NFC; Apple U1 chip ultrawideband",
            "battery": "4500mAh; Fast charging 25W, Fast wireless charging 15W, Reverse wireless charging 4.5W, USB Power Delivery 3.0.",
            "misc": "Fingerprint reader (under display, optical), accelerometer, gyro, proximity, compass, barometer; NFC; stereo speakers."
        },
        {
            "brandName": "motorola",
            "brandID": "motorola",
            "ID": "M04",
            "pic": "../images/motoone5gone.png",
            "pic1": "../images/motog.png",
            "pic2": "../images/motogpower.png",
            "pic3": "../images/motogstylelus.png",
            "pic4": "../images/motoone5gone.png",
            "name": "Motorola One 5G Ace",
            "price": 970,
            "discount": 870,
            "dispercent": 15,
            "gift": "Discount 15%",
            "body": "159.8x74.5x8.4mm, 190g; Glass front, plastic back, aluminum frame; Samsung Pay (Visa, MasterCard certified), IP68 dust/water resistant (up to 1.5m for 30 mins); Colors: Cloud Lavender, Cloud Mint, Cloud Navy, Cloud White, Cloud Red, Cloud Orange.",
            "screen": "6.5 Super AMOLED, 1080x2400px resolution, 20:9 aspect ratio, 407ppi; 120Hz refresh rate.",
            "os": "Android 10, One UI 2.5",
            "chipset": "Qualcomm SM8250 Snapdragon 865 (7 nm+): Octa-core (1x2.84 GHz Kryo 585 & 3x2.42 GHz Kryo 585 & 4x1.8 GHz Kryo 585); Adreno 650.",
            "memory": "128GB 6GB RAM, 128GB 8GB RAM, 256GB 8GB RAM; microSDXC (uses shared SIM slot).",
            "camera": "Wide (main): 12 MP, f/1.8, 26mm, 1/1.76, 1.8µm, Dual Pixel PDAF, OIS; Telephoto: 8 MP, f/2.4, 73mm, 1/4.5, 1.0µm, PDAF, OIS, 3x optical zoom; Ultra wide angle: 12 MP, f/2.2, 123˚, 13mm, 1/3.0, 1.12µm; LED flash, auto-HDR, panorama.",
            "video": "Rear camera: 4K, 1080p, gyro-EIS; Front camera: 4K, 1080p",
            "selfie": "32 MP, f/2.2, 26mm (wide), 1/2.74, 0.8µm; HDR",
            "connectivity": "Dual SIM, 4G LTE (1 Gbps); Wi-Fi a/b/g/n/ac/ax; Bluetooth 5.0; Lightning port; GPS with A-GPS, GLONASS, GALILEO, QZSS; NFC; Apple U1 chip ultrawideband",
            "battery": "4500mAh; Fast charging 25W, Fast wireless charging 15W, Reverse wireless charging 4.5W, USB Power Delivery 3.0.",
            "misc": "Fingerprint reader (under display, optical), accelerometer, gyro, proximity, compass, barometer; NFC; stereo speakers."
        },
        {
            "brandName": "nokia",
            "brandID": "nokia",
            "ID": "N01",
            "pic": "../images/nokiaslim.png",
            "pic1": "../images/nokiaslim.png",
            "pic2": "../images/nokiax50.png",
            "pic3": "../images/nokiax70pro.png",
            "pic4": "../images/nokiaX90.png",
            "name": "Nokia Slim",
            "price": 670,
            "discount": 570,
            "dispercent": 25,
            "gift": "Discount 15%",
            "body": "159.8x74.5x8.4mm, 190g; Glass front, plastic back, aluminum frame; Samsung Pay (Visa, MasterCard certified), IP68 dust/water resistant (up to 1.5m for 30 mins); Colors: Cloud Lavender, Cloud Mint, Cloud Navy, Cloud White, Cloud Red, Cloud Orange.",
            "screen": "6.5 Super AMOLED, 1080x2400px resolution, 20:9 aspect ratio, 407ppi; 120Hz refresh rate.",
            "os": "Android 10, One UI 2.5",
            "chipset": "Qualcomm SM8250 Snapdragon 865 (7 nm+): Octa-core (1x2.84 GHz Kryo 585 & 3x2.42 GHz Kryo 585 & 4x1.8 GHz Kryo 585); Adreno 650.",
            "memory": "128GB 6GB RAM, 128GB 8GB RAM, 256GB 8GB RAM; microSDXC (uses shared SIM slot).",
            "camera": "Wide (main): 12 MP, f/1.8, 26mm, 1/1.76, 1.8µm, Dual Pixel PDAF, OIS; Telephoto: 8 MP, f/2.4, 73mm, 1/4.5, 1.0µm, PDAF, OIS, 3x optical zoom; Ultra wide angle: 12 MP, f/2.2, 123˚, 13mm, 1/3.0, 1.12µm; LED flash, auto-HDR, panorama.",
            "video": "Rear camera: 4K, 1080p, gyro-EIS; Front camera: 4K, 1080p",
            "selfie": "32 MP, f/2.2, 26mm (wide), 1/2.74, 0.8µm; HDR",
            "connectivity": "Dual SIM, 4G LTE (1 Gbps); Wi-Fi a/b/g/n/ac/ax; Bluetooth 5.0; Lightning port; GPS with A-GPS, GLONASS, GALILEO, QZSS; NFC; Apple U1 chip ultrawideband",
            "battery": "4500mAh; Fast charging 25W, Fast wireless charging 15W, Reverse wireless charging 4.5W, USB Power Delivery 3.0.",
            "misc": "Fingerprint reader (under display, optical), accelerometer, gyro, proximity, compass, barometer; NFC; stereo speakers."
        },
        {
            "brandName": "nokia",
            "brandID": "nokia",
            "ID": "N02",
            "pic": "../images/nokiax70pro.png",
            "pic1": "../images/nokiaslim.png",
            "pic2": "../images/nokiax50.png",
            "pic3": "../images/nokiax70pro.png",
            "pic4": "../images/nokiaX90.png",
            "name": "Nokia X70 Pro",
            "price": 870,
            "discount": 770,
            "dispercent": 10,
            "gift": "Discount 20%",
            "body": "159.8x74.5x8.4mm, 190g; Glass front, plastic back, aluminum frame; Samsung Pay (Visa, MasterCard certified), IP68 dust/water resistant (up to 1.5m for 30 mins); Colors: Cloud Lavender, Cloud Mint, Cloud Navy, Cloud White, Cloud Red, Cloud Orange.",
            "screen": "6.5 Super AMOLED, 1080x2400px resolution, 20:9 aspect ratio, 407ppi; 120Hz refresh rate.",
            "os": "Android 10, One UI 2.5",
            "chipset": "Qualcomm SM8250 Snapdragon 865 (7 nm+): Octa-core (1x2.84 GHz Kryo 585 & 3x2.42 GHz Kryo 585 & 4x1.8 GHz Kryo 585); Adreno 650.",
            "memory": "128GB 6GB RAM, 128GB 8GB RAM, 256GB 8GB RAM; microSDXC (uses shared SIM slot).",
            "camera": "Wide (main): 12 MP, f/1.8, 26mm, 1/1.76, 1.8µm, Dual Pixel PDAF, OIS; Telephoto: 8 MP, f/2.4, 73mm, 1/4.5, 1.0µm, PDAF, OIS, 3x optical zoom; Ultra wide angle: 12 MP, f/2.2, 123˚, 13mm, 1/3.0, 1.12µm; LED flash, auto-HDR, panorama.",
            "video": "Rear camera: 4K, 1080p, gyro-EIS; Front camera: 4K, 1080p",
            "selfie": "32 MP, f/2.2, 26mm (wide), 1/2.74, 0.8µm; HDR",
            "connectivity": "Dual SIM, 4G LTE (1 Gbps); Wi-Fi a/b/g/n/ac/ax; Bluetooth 5.0; Lightning port; GPS with A-GPS, GLONASS, GALILEO, QZSS; NFC; Apple U1 chip ultrawideband",
            "battery": "4500mAh; Fast charging 25W, Fast wireless charging 15W, Reverse wireless charging 4.5W, USB Power Delivery 3.0.",
            "misc": "Fingerprint reader (under display, optical), accelerometer, gyro, proximity, compass, barometer; NFC; stereo speakers."
        },
        {
            "brandName": "nokia",
            "brandID": "nokia",
            "ID": "N03",
            "pic": "../images/nokiax90.png",
            "pic1": "../images/nokiaslim.png",
            "pic2": "../images/nokiax50.png",
            "pic3": "../images/nokiax70pro.png",
            "pic4": "../images/nokiaX90.png",
            "name": "Nokia X90",
            "price": 970,
            "discount": 870,
            "dispercent": 15,
            "gift": "Discount 15%",
            "body": "159.8x74.5x8.4mm, 190g; Glass front, plastic back, aluminum frame; Samsung Pay (Visa, MasterCard certified), IP68 dust/water resistant (up to 1.5m for 30 mins); Colors: Cloud Lavender, Cloud Mint, Cloud Navy, Cloud White, Cloud Red, Cloud Orange.",
            "screen": "6.5 Super AMOLED, 1080x2400px resolution, 20:9 aspect ratio, 407ppi; 120Hz refresh rate.",
            "os": "Android 10, One UI 2.5",
            "chipset": "Qualcomm SM8250 Snapdragon 865 (7 nm+): Octa-core (1x2.84 GHz Kryo 585 & 3x2.42 GHz Kryo 585 & 4x1.8 GHz Kryo 585); Adreno 650.",
            "memory": "128GB 6GB RAM, 128GB 8GB RAM, 256GB 8GB RAM; microSDXC (uses shared SIM slot).",
            "camera": "Wide (main): 12 MP, f/1.8, 26mm, 1/1.76, 1.8µm, Dual Pixel PDAF, OIS; Telephoto: 8 MP, f/2.4, 73mm, 1/4.5, 1.0µm, PDAF, OIS, 3x optical zoom; Ultra wide angle: 12 MP, f/2.2, 123˚, 13mm, 1/3.0, 1.12µm; LED flash, auto-HDR, panorama.",
            "video": "Rear camera: 4K, 1080p, gyro-EIS; Front camera: 4K, 1080p",
            "selfie": "32 MP, f/2.2, 26mm (wide), 1/2.74, 0.8µm; HDR",
            "connectivity": "Dual SIM, 4G LTE (1 Gbps); Wi-Fi a/b/g/n/ac/ax; Bluetooth 5.0; Lightning port; GPS with A-GPS, GLONASS, GALILEO, QZSS; NFC; Apple U1 chip ultrawideband",
            "battery": "4500mAh; Fast charging 25W, Fast wireless charging 15W, Reverse wireless charging 4.5W, USB Power Delivery 3.0.",
            "misc": "Fingerprint reader (under display, optical), accelerometer, gyro, proximity, compass, barometer; NFC; stereo speakers."
        },
        {
            "brandName": "nokia",
            "brandID": "nokia",
            "ID": "N04",
            "pic": "../images/nokiax50.png",
            "pic1": "../images/nokiaslim.png",
            "pic2": "../images/nokiax50.png",
            "pic3": "../images/nokiax70pro.png",
            "pic4": "../images/nokiaX90.png",
            "name": "Nokia X50 Pro",
            "price": 970,
            "discount": 870,
            "dispercent": 15,
            "gift": "Discount 15%",
            "body": "159.8x74.5x8.4mm, 190g; Glass front, plastic back, aluminum frame; Samsung Pay (Visa, MasterCard certified), IP68 dust/water resistant (up to 1.5m for 30 mins); Colors: Cloud Lavender, Cloud Mint, Cloud Navy, Cloud White, Cloud Red, Cloud Orange.",
            "screen": "6.5 Super AMOLED, 1080x2400px resolution, 20:9 aspect ratio, 407ppi; 120Hz refresh rate.",
            "os": "Android 10, One UI 2.5",
            "chipset": "Qualcomm SM8250 Snapdragon 865 (7 nm+): Octa-core (1x2.84 GHz Kryo 585 & 3x2.42 GHz Kryo 585 & 4x1.8 GHz Kryo 585); Adreno 650.",
            "memory": "128GB 6GB RAM, 128GB 8GB RAM, 256GB 8GB RAM; microSDXC (uses shared SIM slot).",
            "camera": "Wide (main): 12 MP, f/1.8, 26mm, 1/1.76, 1.8µm, Dual Pixel PDAF, OIS; Telephoto: 8 MP, f/2.4, 73mm, 1/4.5, 1.0µm, PDAF, OIS, 3x optical zoom; Ultra wide angle: 12 MP, f/2.2, 123˚, 13mm, 1/3.0, 1.12µm; LED flash, auto-HDR, panorama.",
            "video": "Rear camera: 4K, 1080p, gyro-EIS; Front camera: 4K, 1080p",
            "selfie": "32 MP, f/2.2, 26mm (wide), 1/2.74, 0.8µm; HDR",
            "connectivity": "Dual SIM, 4G LTE (1 Gbps); Wi-Fi a/b/g/n/ac/ax; Bluetooth 5.0; Lightning port; GPS with A-GPS, GLONASS, GALILEO, QZSS; NFC; Apple U1 chip ultrawideband",
            "battery": "4500mAh; Fast charging 25W, Fast wireless charging 15W, Reverse wireless charging 4.5W, USB Power Delivery 3.0.",
            "misc": "Fingerprint reader (under display, optical), accelerometer, gyro, proximity, compass, barometer; NFC; stereo speakers."
        }
    ]
}